cache/robots/modrob-gen2/make_zimmer_gripper.py
cache/robots/modrob-gen2/tests/test_loadable.py
timor/Bodies.py
timor/Geometry.py
timor/Joints.py
timor/Module.py
timor/Robot.py
timor/Volume.py
timor/__init__.py
timor/parameterized.py
timor/configuration_search/AssemblyFilter.py
timor/configuration_search/AssemblyIterator.py
timor/configuration_search/GA.py
timor/configuration_search/LiuIterator.py
timor/configuration_search/__init__.py
timor/task/Constraints.py
timor/task/CostFunctions.py
timor/task/Goals.py
timor/task/Obstacle.py
timor/task/Solution.py
timor/task/Task.py
timor/task/Tolerance.py
timor/task/__init__.py
timor/utilities/__init__.py
timor/utilities/asset_handling.py
timor/utilities/callbacks.py
timor/utilities/configurations.py
timor/utilities/download_data.py
timor/utilities/dtypes.py
timor/utilities/errors.py
timor/utilities/file_locations.py
timor/utilities/frames.py
timor/utilities/json_serialization_formatting.py
timor/utilities/jsonable.py
timor/utilities/logging.py
timor/utilities/module_classification.py
timor/utilities/prebuilt_robots.py
timor/utilities/schema.py
timor/utilities/spatial.py
timor/utilities/tolerated_pose.py
timor/utilities/trajectory.py
timor/utilities/transformation.py
timor/utilities/visualization.py
timor/utilities/write_urdf.py
timor_sample_robots/IMPROV/modules.json
timor_sample_robots/IMPROV/STLfiles/L1.stl
timor_sample_robots/IMPROV/STLfiles/L10.stl
timor_sample_robots/IMPROV/STLfiles/L2.stl
timor_sample_robots/IMPROV/STLfiles/L3.stl
timor_sample_robots/IMPROV/STLfiles/L8.stl
timor_sample_robots/IMPROV/STLfiles/L9.stl
timor_sample_robots/IMPROV/STLfiles/convexDecompose/L1.stl.wrl
timor_sample_robots/IMPROV/STLfiles/convexDecompose/L2.stl.wrl
timor_sample_robots/IMPROV/STLfiles/convexDecompose/L3.stl.wrl
timor_sample_robots/IMPROV/STLfiles/convexDecompose/L8.stl.wrl
timor_sample_robots/IMPROV/STLfiles/convexDecompose/L9.stl.wrl
timor_sample_robots/geometric_primitive_modules/modules.json
timor_sample_robots/panda/LICENSE
timor_python-1.0.dist-info/LICENSE
timor_python-1.0.dist-info/METADATA
timor_python-1.0.dist-info/WHEEL
timor_python-1.0.dist-info/top_level.txt
timor_python-1.0.dist-info/RECORD
