Metadata-Version: 2.1
Name: timor-python
Version: 1.0
Summary: Toolbox for Industrial Modular Robots
Author-email: Jonathan Kuelz <jonathan.kuelz@tum.de>
License: MIT
Project-URL: Source Code, https://gitlab.lrz.de/tum-cps/timor-python
Project-URL: Documentation, https://timor-python.readthedocs.io/en/latest/
Project-URL: Bug Tracker, https://gitlab.lrz.de/tum-cps/timor-python/-/issues
Keywords: Modular Reconfigurable Robots,Robot Design,Model Generation,Simulation
Classifier: License :: OSI Approved :: MIT License
Classifier: Programming Language :: Python
Classifier: Programming Language :: Python :: 3
Classifier: Programming Language :: Python :: 3 :: Only
Requires-Python: >=3.8
License-File: LICENSE
Requires-Dist: jsonschema >=4.10
Requires-Dist: pin >2.6.12
Requires-Dist: pygad >=3.0.0
Requires-Dist: matplotlib >=3.5.1
Requires-Dist: meshcat
Requires-Dist: networkx >=2.6.3
Requires-Dist: numpy >=1.21.0
Requires-Dist: roboticstoolbox-python >=0.11.0
Requires-Dist: scipy <1.12.0,>=1.6
Requires-Dist: requests >=2.28.1
Provides-Extra: dev
Requires-Dist: coverage >=6.3 ; extra == 'dev'
Requires-Dist: flake8 >=5.0 ; extra == 'dev'
Requires-Dist: ipykernel ; extra == 'dev'
Requires-Dist: nbclient ; extra == 'dev'
Requires-Dist: nbformat ; extra == 'dev'
Requires-Dist: nbconvert ; extra == 'dev'
Requires-Dist: pre-commit ; extra == 'dev'
Requires-Dist: pip-tools ; extra == 'dev'
Requires-Dist: pytest >=6.0 ; extra == 'dev'
Requires-Dist: setuptools >=61.0.0 ; extra == 'dev'
Requires-Dist: tqdm >=4.0 ; extra == 'dev'
Provides-Extra: full
Requires-Dist: timor-python[dev] ; extra == 'full'
Requires-Dist: timor-python[optimization] ; extra == 'full'
Requires-Dist: jupyterlab ; extra == 'full'
Requires-Dist: trimesh >=3.18 ; extra == 'full'
Provides-Extra: optimization
Requires-Dist: optuna >=3.1 ; extra == 'optimization'
Requires-Dist: optuna-dashboard >=0.10 ; extra == 'optimization'
Requires-Dist: plotly ; extra == 'optimization'
Requires-Dist: scikit-learn ; extra == 'optimization'
Requires-Dist: wandb >=0.15 ; extra == 'optimization'
